coordextract/.gitpod.Dockerfile
coordextract/__init__.py
coordextract/cli.py
coordextract/conversion_utils.py
coordextract/core.py
coordextract/gpx_utils.py
coordextract/point.py
coordextract/py.typed
coordextract-0.1.3.dist-info/LICENSE
coordextract-0.1.3.dist-info/METADATA
coordextract-0.1.3.dist-info/WHEEL
coordextract-0.1.3.dist-info/entry_points.txt
coordextract-0.1.3.dist-info/RECORD
