Metadata-Version: 2.1
Name: coordextract
Version: 0.1.3
Summary: coordextract is a Python library and CLI tool for converting data from GPX files into pydantic models and adding MGRS coordinates to the data. The CLI will return the data in JSON format.
License: MIT
Author: Sean McLeaish
Author-email: smcleaish@gmail.com
Requires-Python: >=3.10,<3.12
Classifier: License :: OSI Approved :: MIT License
Classifier: Programming Language :: Python :: 3
Classifier: Programming Language :: Python :: 3.10
Classifier: Programming Language :: Python :: 3.11
Requires-Dist: aiofiles (>=23.2.1,<24.0.0)
Requires-Dist: lxml (>=5.1.0,<6.0.0)
Requires-Dist: magika (>=0.5.0,<0.6.0)
Requires-Dist: mgrs (>=1.4.6,<2.0.0)
Requires-Dist: pydantic (>=2.6.1,<3.0.0)
Requires-Dist: typer (>=0.9.0,<0.10.0)
